{
    "title": "Stirring the Deep",
    "type": "DEAD",
    "image": "/images/barn_ice.png",
    "lines": [
        "You pick up a jagged rock and toss it into the center of the dark, subterranean lake. The ripples spread silently.",
        "Suddenly, the water explodes upward. A massive, pale tentacle lashes out, dragging you into the freezing depths.",
        "The lake is silent once more."
    ],
    "options": [
        {
            "id": "restart",
            "link": "index.json",
            "desc": "Restart from the tent"
        }
    ]
}
