{
    "title": "The Sewer Network",
    "image": "/images/sewer.png",
    "imageClass": "hue-rotate-[80deg] saturate-150 brightness-60 contrast-125",
    "lines": [
        "The air in the sewers is surprisingly cold, carrying the faint, chemical tang of old machinery and stagnant water.",
        "The brick walls are slick with a bioluminescent emerald moss that provides just enough light to see the ripples in the dark water below.",
        "From the darkness ahead, you hear the rhythmic *thrum-thrum* of a massive pump that should have died years ago."
    ],
    "options": [
        {
            "id": "left",
            "link": "sewer_left.json",
            "desc": "1. Follow the narrow walkway to the left"
        },
        {
            "id": "right",
            "link": "sewer_right.json",
            "desc": "2. Wades through the shallow water to the right"
        },
        {
            "id": "back",
            "link": "village.json",
            "desc": "3. Climb back up the ladder to the square"
        }
    ]
}
